scientific_plot_scaler/__init__.py
scientific_plot_scaler/plot_scaler.py
scientific_plot_scaler/configs/ieee_journal.json
scientific_plot_scaler/configs/nature_journal.json
scientific_plot_scaler/configs/presentation.json
scientific_plot_scaler/configs/thesis_single.json
scientific_plot_scaler-1.0.0.dist-info/licenses/LICENSE.md
scientific_plot_scaler-1.0.0.dist-info/METADATA
scientific_plot_scaler-1.0.0.dist-info/WHEEL
scientific_plot_scaler-1.0.0.dist-info/entry_points.txt
scientific_plot_scaler-1.0.0.dist-info/top_level.txt
scientific_plot_scaler-1.0.0.dist-info/RECORD
