Metadata-Version: 2.4
Name: scientific-plot-scaler
Version: 1.0.0
Summary: A tool for creating publication-ready scientific plots with proper text scaling for LaTeX documents
Home-page: https://github.com/VijayN10/scientific-plot-scaler
Author: Vijay Nandurdikar
Author-email: Vijay Nandurdikar <vijaynandurdikar@gmail.com>
Maintainer-email: Vijay Nandurdikar <vijaynandurdikar@gmail.com>
License: MIT
Project-URL: Homepage, https://github.com/VijayN10/scientific-plot-scaler
Project-URL: Documentation, https://github.com/VijayN10/scientific-plot-scaler/wiki
Project-URL: Repository, https://github.com/VijayN10/scientific-plot-scaler
Project-URL: Bug Tracker, https://github.com/VijayN10/scientific-plot-scaler/issues
Project-URL: Changelog, https://github.com/VijayN10/scientific-plot-scaler/blob/main/CHANGELOG.md
Keywords: scientific,plotting,latex,publication,matplotlib
Classifier: Development Status :: 4 - Beta
Classifier: Intended Audience :: Science/Research
Classifier: Topic :: Scientific/Engineering :: Visualization
Classifier: License :: OSI Approved :: MIT License
Classifier: Programming Language :: Python :: 3
Classifier: Programming Language :: Python :: 3.8
Classifier: Programming Language :: Python :: 3.9
Classifier: Programming Language :: Python :: 3.10
Classifier: Programming Language :: Python :: 3.11
Classifier: Operating System :: OS Independent
Requires-Python: >=3.8
License-File: LICENSE.md
Requires-Dist: matplotlib>=3.5.0
Requires-Dist: seaborn>=0.11.0
Requires-Dist: numpy>=1.20.0
Requires-Dist: scipy>=1.7.0
Provides-Extra: dev
Requires-Dist: pytest>=6.0; extra == "dev"
Requires-Dist: pytest-cov>=2.0; extra == "dev"
Requires-Dist: black>=21.0; extra == "dev"
Requires-Dist: flake8>=3.8; extra == "dev"
Requires-Dist: mypy>=0.812; extra == "dev"
Requires-Dist: pre-commit>=2.0; extra == "dev"
Provides-Extra: examples
Requires-Dist: jupyter>=1.0; extra == "examples"
Requires-Dist: pandas>=1.0; extra == "examples"
Provides-Extra: docs
Requires-Dist: sphinx>=4.0; extra == "docs"
Requires-Dist: sphinx-rtd-theme>=1.0; extra == "docs"
Dynamic: author
Dynamic: home-page
Dynamic: license-file
Dynamic: requires-python
